README.rst
setup.py
rescheduler/__about__.py
rescheduler/__init__.py
rescheduler/job.py
rescheduler/scheduler.py
rescheduler.egg-info/PKG-INFO
rescheduler.egg-info/SOURCES.txt
rescheduler.egg-info/dependency_links.txt
rescheduler.egg-info/requires.txt
rescheduler.egg-info/top_level.txt