Metadata-Version: 1.2
Name: rescheduler
Version: 0.1.0
Summary: Python redis scheduler
Home-page: https://github.com/dapper91/rescheduler
Author: Dmitry Pershin
Author-email: dapper91@mail.ru
License: Public Domain License
Project-URL: Source, https://github.com/dapper91/rescheduler
Keywords: scheduler,redis,distributed-scheduler
Platform: UNKNOWN
Classifier: Development Status :: 4 - Beta
Classifier: Intended Audience :: Developers
Classifier: Natural Language :: English
Classifier: License :: Public Domain
Classifier: Programming Language :: Python
Classifier: Programming Language :: Python :: 3.7
Classifier: Programming Language :: Python :: 3.8
Classifier: Programming Language :: Python :: 3.9
Requires-Python: >=3.7
